astrowidgets/__init__.py
astrowidgets/bqplot.py
astrowidgets/ginga.py
astrowidgets/version.py
astrowidgets/tests/__init__.py
astrowidgets/tests/_test_widget_api_ginga.py
astrowidgets/tests/test_widget_api_bqplot.py
astrowidgets-0.4.0.dist-info/licenses/LICENSE.rst
astrowidgets-0.4.0.dist-info/METADATA
astrowidgets-0.4.0.dist-info/WHEEL
astrowidgets-0.4.0.dist-info/top_level.txt
astrowidgets-0.4.0.dist-info/RECORD
