Metadata-Version: 2.4
Name: astrowidgets
Version: 0.4.0
Summary: Widgets for the Jupyter notebook and JupyterLab
Home-page: https://astrowidgets.readthedocs.io
Author: Astropy Developers
Author-email: mattwcraig@gmail.com
License: BSD 3-Clause
License-File: LICENSE.rst
Requires-Dist: astropy
Requires-Dist: astro-image-display-api>=0.1.2
Requires-Dist: ginga>=3.4
Requires-Dist: pillow
Requires-Dist: ipywidgets>=8
Requires-Dist: ipyevents>=0.6.3
Requires-Dist: jupyterlab>=3
Requires-Dist: aggdraw
Requires-Dist: bqplot
Requires-Dist: bqplot-image-gl
Requires-Dist: matplotlib
Provides-Extra: test
Requires-Dist: pytest-astropy; extra == "test"
Requires-Dist: pytest-cov; extra == "test"
Provides-Extra: docs
Requires-Dist: sphinx-astropy; extra == "docs"
Dynamic: license-file
